gmdm/__init__.py
gmdm/app.py
gmdm/cli.py
gmdm/defaults.py
gmdm/models.py
gmdm/ops.py
gmdm/utils/dicts.py
gmdm/utils/files.py
gmdm/utils/logging.py
gmdm/utils/strings.py
gmdm-0.2.8.dist-info/LICENSE.md
gmdm-0.2.8.dist-info/METADATA
gmdm-0.2.8.dist-info/WHEEL
gmdm-0.2.8.dist-info/entry_points.txt
gmdm-0.2.8.dist-info/top_level.txt
gmdm-0.2.8.dist-info/RECORD
