Metadata-Version: 2.1
Name: gmdm
Version: 0.2.8
Summary: The GMDM CLI tool for managing dependencies of GameMaker projects and files.
Author-email: Kenan Masri <kenanmasri@outlook.com>
License: MIT License
Project-URL: Bug Tracker, https://github.com/knno/gmdm/issues
Keywords: gamemaker,gml,dependencies,export,libraries
Classifier: Programming Language :: Python :: 3
Classifier: License :: OSI Approved :: MIT License
Classifier: Operating System :: OS Independent
Requires-Python: >=3.11
License-File: LICENSE.md
Requires-Dist: coloredlogs
Requires-Dist: PyYAML
Requires-Dist: json5
